peripherals/uart/rx_uart.v
module rx_uart(
	input i_clk,
	input i_rst,
	input [3:0] sel_baud,
	input i_Rx,
	output reg [7:0] o_Data
	);
	integer baud_rate;
	integer hold_len;
	integer sample;
	//parameter baud_rate = 9600; //bits per second, must be same on Tx and Rx 
	//parameter hold_len = 1000000/baud_rate; //clocks the bits are valid for. Default 100mHz i_clk
	//parameter hold_len = 5;
	//parameter sample = (hold_len - 1) /2;
	parameter clk_freq = 1000000; //Need to know internal clock frequency to configure sample time 
	
	parameter IDLE = 0;
	parameter START = 1;
	parameter DATA = 2;
	parameter PARITY = 3;
	parameter STOP = 4;
	reg [7:0] temp;
	reg [2:0] Rx_state;
	reg [7:0] clk_count;
	reg [3:0] data_count;
	always @(posedge i_clk) begin
		//$display("State = %3b", Rx_state);
		if (i_rst) begin
			case (Rx_state)
				IDLE: begin
					clk_count <= 0;
					if (~i_Rx) begin //Check for Rx pulldown to start
						//$display("[%0t] Start bit recieved", $time);
						Rx_state <= START;
						o_Data = 0;
						clk_count <= 1;
						end
					else begin
						Rx_state <= IDLE;
					end
				end
				START: begin
					if (clk_count == sample) begin //check in the middle of the signal
						if(i_Rx) begin	
							Rx_state <= IDLE;
							//$display("%b i_Rx", i_Rx);
							//$display("[%0t] Sample = %d Return to Idle", $time, sample);
						end
					end
					else if (clk_count == hold_len) begin //Finish start bit period
						//$display("Moving to DATA recieve");
						Rx_state <= DATA;
						clk_count = 1;
						data_count = 0;
					end
					else begin
						Rx_state <= START;
					end
					clk_count <= clk_count + 1;
				end
				DATA: begin
					if(data_count == 8) begin //data frame completed
						Rx_state <= STOP;
						clk_count = 1;
						o_Data = temp;
						$display("Done recieving");
						//$display("%7b", o_Data);
						end
					else if (clk_count == hold_len) begin
						clk_count = 0;
						//$display("One bit complete");
						end
					else if(clk_count == sample) begin
						//$display("sampling: %b", i_Rx);
						//o_Data[7] = i_Rx; //LSB received first, MSB recieved last
						temp[7] = i_Rx; //LSB received first, MSB recieved last
						if(data_count < 7) begin
							temp  = temp >> 1; //RSH to make room for next data
						end
						data_count = data_count + 1;
						end
					else begin
						Rx_state <= DATA;
					end
					clk_count = clk_count + 1;
				end
				STOP: begin
					if (clk_count == sample) begin //check in the middle of the signal
						if(~i_Rx) begin	
							//TODO error handler
							//$display("%b i_Rx", i_Rx);
							//display("[%0t] Sample = %d Return to Idle", $time, sample);
						end
					end
					else if (clk_count == hold_len) begin //Finish start bit period
						//$display("STOP bit recieved");
						//$display("Return to IDLE");
						Rx_state <= IDLE;
						clk_count = 0;
						data_count = 0;
					end
					else begin
						Rx_state <= STOP;
					end
					clk_count <= clk_count + 1;
				end
				default: Rx_state <= IDLE;
			endcase
		end
	end
	always @(negedge i_rst) begin
		$display("[%0t] Resetting..", $time);
		case (sel_baud) 
			4'b0000: baud_rate = 9600;
			4'b0001: baud_rate = 110;
			4'b0010: baud_rate = 300;
			4'b0011: baud_rate = 600;
			4'b0100: baud_rate = 1200;
			4'b0101: baud_rate = 2400;
			4'b0110: baud_rate = 4800;
			4'b0111: baud_rate = 14400;
			4'b1000: baud_rate = 19200;
			4'b1001: baud_rate = 38400;
			4'b1010: baud_rate = 57600;
			4'b1011: baud_rate = 115200;
			4'b1100: baud_rate = 128000;
			4'b1101: baud_rate = 256000;
			default: baud_rate = 9600;
		endcase
		hold_len = clk_freq / baud_rate;
		sample = hold_len / 2;
		$display("Internal Clock frequency is %d", clk_freq);
		$display("Baud rate is %d", baud_rate);
		$display("Sampling at %d", sample);
		Rx_state <= IDLE;
	end 
endmodule

peripherals/uart/tb_uart.v
`timescale 1ns / 1 ns

module main;
reg i_clk;
reg i_rst;
reg i_Rx;
reg [3:0] sel_baud;
wire [7:0] o_Data;


parameter clk_rate = 1000000;
parameter baud_rate = 9600;
//parameter hold_len = 5000;
parameter hold_len = clk_rate/baud_rate*1000;


rx_uart test(i_clk, i_rst, sel_baud, i_Rx, o_Data);
//100mHz, 1000ns period
always #500 i_clk = ~i_clk; 


reg [7:0] clks;
reg active;
reg [95:0] result;
reg [7:0] t0,t1,t2,t3,t4,t5,t6,t7,t8,t9,t10,t11,t12;
initial begin
	$dumpfile("dump.vcd");
	$dumpvars(0, main);
end
initial begin
	clks = 0;
	active = 0;
	i_clk = 0;
	i_rst = 0;
	i_Rx = 1;
	sel_baud = 0;
	#1000
	i_rst = 1;
	#100000000000000000000
	$finish;
end

task drive(input val);
	begin
		//$display("[%0t] Driving %0b", $time, val);
		i_Rx = val;
		#(hold_len);
	end
endtask

task stop;
	begin
		drive(1);
		//$display("Sending STOP bit");
	end
endtask

task start;
	begin
		drive(0);
		//$display("Sending START bit");
	end
endtask
task sendByte(input [7:0] c);
	begin
		//$display("Sending: %c", c);
		start();
		for(integer i = 0; i < 8; i=i+1) begin
			//$display("Sending bit");
			drive(c[i]);
		end
		stop();
		$display("Recieved: %c", o_Data);
	end
endtask

initial begin
	#1000
	active = 1;
	sendByte("A");
	sendByte("B");
	sendByte("C");
	sendByte("D");
	$finish;
end

always @(posedge i_clk) begin
	if(active) begin
		clks = clks + 1;
	end
end

	
endmodule

peripherals/uart/dump.vcd
$date
	Mon Feb 13 00:29:15 2023
$end
$version
	Icarus Verilog
$end
$timescale
	1ns
$end
$scope module main $end
$var wire 8 ! o_Data [7:0] $end
$var reg 1 " active $end
$var reg 8 # clks [7:0] $end
$var reg 1 $ i_Rx $end
$var reg 1 % i_clk $end
$var reg 1 & i_rst $end
$var reg 4 ' sel_baud [3:0] $end
$scope module test $end
$var wire 1 $ i_Rx $end
$var wire 1 % i_clk $end
$var wire 1 & i_rst $end
$var wire 4 ( sel_baud [3:0] $end
$var reg 3 ) Rx_state [2:0] $end
$var reg 8 * clk_count [7:0] $end
$var reg 4 + data_count [3:0] $end
$var reg 8 , o_Data [7:0] $end
$var reg 8 - temp [7:0] $end
$var integer 32 . baud_rate [31:0] $end
$var integer 32 / hold_len [31:0] $end
$var integer 32 0 sample [31:0] $end
$upscope $end
$scope task drive $end
$var reg 1 1 val $end
$upscope $end
$scope task sendByte $end
$var reg 8 2 c [7:0] $end
$scope begin $ivl_for_loop0 $end
$var integer 32 3 i [31:0] $end
$upscope $end
$upscope $end
$scope task start $end
$upscope $end
$scope task stop $end
$upscope $end
$upscope $end
$enddefinitions $end
#0
$dumpvars
bx 3
bx 2
x1
b110100 0
b1101000 /
b10010110000000 .
bx -
bx ,
bx +
bx *
b0 )
b0 (
b0 '
0&
0%
1$
b0 #
0"
bx !
$end
#500
1%
#1000
0%
0$
01
b1010000 2
1"
1&
#1500
b1 )
b1 *
b1 #
b0 !
b0 ,
1%
#2000
0%
#2500
b10 *
b10 #
1%
#3000
0%
#3500
b11 *
b11 #
1%
#4000
0%
#4500
b100 *
b100 #
1%
#5000
0%
#5500
b101 *
b101 #
1%
#6000
0%
#6500
b110 *
b110 #
1%
#7000
0%
#7500
b111 *
b111 #
1%
#8000
0%
#8500
b1000 *
b1000 #
1%
#9000
0%
#9500
b1001 *
b1001 #
1%
#10000
0%
#10500
b1010 *
b1010 #
1%
#11000
0%
#11500
b1011 *
b1011 #
1%
#12000
0%
#12500
b1100 *
b1100 #
1%
#13000
0%
#13500
b1101 *
b1101 #
1%
#14000
0%
#14500
b1110 *
b1110 #
1%
#15000
0%
#15500
b1111 *
b1111 #
1%
#16000
0%
#16500
b10000 *
b10000 #
1%
#17000
0%
#17500
b10001 *
b10001 #
1%
#18000
0%
#18500
b10010 *
b10010 #
1%
#19000
0%
#19500
b10011 *
b10011 #
1%
#20000
0%
#20500
b10100 *
b10100 #
1%
#21000
0%
#21500
b10101 *
b10101 #
1%
#22000
0%
#22500
b10110 *
b10110 #
1%
#23000
0%
#23500
b10111 *
b10111 #
1%
#24000
0%
#24500
b11000 *
b11000 #
1%
#25000
0%
#25500
b11001 *
b11001 #
1%
#26000
0%
#26500
b11010 *
b11010 #
1%
#27000
0%
#27500
b11011 *
b11011 #
1%
#28000
0%
#28500
b11100 *
b11100 #
1%
#29000
0%
#29500
b11101 *
b11101 #
1%
#30000
0%
#30500
b11110 *
b11110 #
1%
#31000
0%
#31500
b11111 *
b11111 #
1%
#32000
0%
#32500
b100000 *
b100000 #
1%
#33000
0%
#33500
b100001 *
b100001 #
1%
#34000
0%
#34500
b100010 *
b100010 #
1%
#35000
0%
#35500
b100011 *
b100011 #
1%
#36000
0%
#36500
b100100 *
b100100 #
1%
#37000
0%
#37500
b100101 *
b100101 #
1%
#38000
0%
#38500
b100110 *
b100110 #
1%
#39000
0%
#39500
b100111 *
b100111 #
1%
#40000
0%
#40500
b101000 *
b101000 #
1%
#41000
0%
#41500
b101001 *
b101001 #
1%
#42000
0%
#42500
b101010 *
b101010 #
1%
#43000
0%
#43500
b101011 *
b101011 #
1%
#44000
0%
#44500
b101100 *
b101100 #
1%
#45000
0%
#45500
b101101 *
b101101 #
1%
#46000
0%
#46500
b101110 *
b101110 #
1%
#47000
0%
#47500
b101111 *
b101111 #
1%
#48000
0%
#48500
b110000 *
b110000 #
1%
#49000
0%
#49500
b110001 *
b110001 #
1%
#50000
0%
#50500
b110010 *
b110010 #
1%
#51000
0%
#51500
b110011 *
b110011 #
1%
#52000
0%
#52500
b110100 *
b110100 #
1%
#53000
0%
#53500
b110101 *
b110101 #
1%
#54000
0%
#54500
b110110 *
b110110 #
1%
#55000
0%
#55500
b110111 *
b110111 #
1%
#56000
0%
#56500
b111000 *
b111000 #
1%
#57000
0%
#57500
b111001 *
b111001 #
1%
#58000
0%
#58500
b111010 *
b111010 #
1%
#59000
0%
#59500
b111011 *
b111011 #
1%
#60000
0%
#60500
b111100 *
b111100 #
1%
#61000
0%
#61500
b111101 *
b111101 #
1%
#62000
0%
#62500
b111110 *
b111110 #
1%
#63000
0%
#63500
b111111 *
b111111 #
1%
#64000
0%
#64500
b1000000 *
b1000000 #
1%
#65000
0%
#65500
b1000001 *
b1000001 #
1%
#66000
0%
#66500
b1000010 *
b1000010 #
1%
#67000
0%
#67500
b1000011 *
b1000011 #
1%
#68000
0%
#68500
b1000100 *
b1000100 #
1%
#69000
0%
#69500
b1000101 *
b1000101 #
1%
#70000
0%
#70500
b1000110 *
b1000110 #
1%
#71000
0%
#71500
b1000111 *
b1000111 #
1%
#72000
0%
#72500
b1001000 *
b1001000 #
1%
#73000
0%
#73500
b1001001 *
b1001001 #
1%
#74000
0%
#74500
b1001010 *
b1001010 #
1%
#75000
0%
#75500
b1001011 *
b1001011 #
1%
#76000
0%
#76500
b1001100 *
b1001100 #
1%
#77000
0%
#77500
b1001101 *
b1001101 #
1%
#78000
0%
#78500
b1001110 *
b1001110 #
1%
#79000
0%
#79500
b1001111 *
b1001111 #
1%
#80000
0%
#80500
b1010000 *
b1010000 #
1%
#81000
0%
#81500
b1010001 *
b1010001 #
1%
#82000
0%
#82500
b1010010 *
b1010010 #
1%
#83000
0%
#83500
b1010011 *
b1010011 #
1%
#84000
0%
#84500
b1010100 *
b1010100 #
1%
#85000
0%
#85500
b1010101 *
b1010101 #
1%
#86000
0%
#86500
b1010110 *
b1010110 #
1%
#87000
0%
#87500
b1010111 *
b1010111 #
1%
#88000
0%
#88500
b1011000 *
b1011000 #
1%
#89000
0%
#89500
b1011001 *
b1011001 #
1%
#90000
0%
#90500
b1011010 *
b1011010 #
1%
#91000
0%
#91500
b1011011 *
b1011011 #
1%
#92000
0%
#92500
b1011100 *
b1011100 #
1%
#93000
0%
#93500
b1011101 *
b1011101 #
1%
#94000
0%
#94500
b1011110 *
b1011110 #
1%
#95000
0%
#95500
b1011111 *
b1011111 #
1%
#96000
0%
#96500
b1100000 *
b1100000 #
1%
#97000
0%
#97500
b1100001 *
b1100001 #
1%
#98000
0%
#98500
b1100010 *
b1100010 #
1%
#99000
0%
#99500
b1100011 *
b1100011 #
1%
#100000
0%
#100500
b1100100 *
b1100100 #
1%
#101000
0%
#101500
b1100101 *
b1100101 #
1%
#102000
0%
#102500
b1100110 *
b1100110 #
1%
#103000
0%
#103500
b1100111 *
b1100111 #
1%
#104000
0%
#104500
b1101000 *
b1101000 #
1%
#105000
0%
b0 3
#105500
b10 )
b1101001 #
b0 +
b10 *
1%
#106000
0%
#106500
b11 *
b1101010 #
1%
#107000
0%
#107500
b1101011 #
b100 *
1%
#108000
0%
#108500
b101 *
b1101100 #
1%
#109000
0%
#109500
b1101101 #
b110 *
1%
#110000
0%
#110500
b111 *
b1101110 #
1%
#111000
0%
#111500
b1101111 #
b1000 *
1%
#112000
0%
#112500
b1001 *
b1110000 #
1%
#113000
0%
#113500
b1110001 #
b1010 *
1%
#114000
0%
#114500
b1011 *
b1110010 #
1%
#115000
0%
#115500
b1110011 #
b1100 *
1%
#116000
0%
#116500
b1101 *
b1110100 #
1%
#117000
0%
#117500
b1110101 #
b1110 *
1%
#118000
0%
#118500
b1111 *
b1110110 #
1%
#119000
0%
#119500
b1110111 #
b10000 *
1%
#120000
0%
#120500
b10001 *
b1111000 #
1%
#121000
0%
#121500
b1111001 #
b10010 *
1%
#122000
0%
#122500
b10011 *
b1111010 #
1%
#123000
0%
#123500
b1111011 #
b10100 *
1%
#124000
0%
#124500
b10101 *
b1111100 #
1%
#125000
0%
#125500
b1111101 #
b10110 *
1%
#126000
0%
#126500
b10111 *
b1111110 #
1%
#127000
0%
#127500
b1111111 #
b11000 *
1%
#128000
0%
#128500
b11001 *
b10000000 #
1%
#129000
0%
#129500
b10000001 #
b11010 *
1%
#130000
0%
#130500
b11011 *
b10000010 #
1%
#131000
0%
#131500
b10000011 #
b11100 *
1%
#132000
0%
#132500
b11101 *
b10000100 #
1%
#133000
0%
#133500
b10000101 #
b11110 *
1%
#134000
0%
#134500
b11111 *
b10000110 #
1%
#135000
0%
#135500
b10000111 #
b100000 *
1%
#136000
0%
#136500
b100001 *
b10001000 #
1%
#137000
0%
#137500
b10001001 #
b100010 *
1%
#138000
0%
#138500
b100011 *
b10001010 #
1%
#139000
0%
#139500
b10001011 #
b100100 *
1%
#140000
0%
#140500
b100101 *
b10001100 #
1%
#141000
0%
#141500
b10001101 #
b100110 *
1%
#142000
0%
#142500
b100111 *
b10001110 #
1%
#143000
0%
#143500
b10001111 #
b101000 *
1%
#144000
0%
#144500
b101001 *
b10010000 #
1%
#145000
0%
#145500
b10010001 #
b101010 *
1%
#146000
0%
#146500
b101011 *
b10010010 #
1%
#147000
0%
#147500
b10010011 #
b101100 *
1%
#148000
0%
#148500
b101101 *
b10010100 #
1%
#149000
0%
#149500
b10010101 #
b101110 *
1%
#150000
0%
#150500
b101111 *
b10010110 #
1%
#151000
0%
#151500
b10010111 #
b110000 *
1%
#152000
0%
#152500
b110001 *
b10011000 #
1%
#153000
0%
#153500
b10011001 #
b110010 *
1%
#154000
0%
#154500
b110011 *
b10011010 #
1%
#155000
0%
#155500
b10011011 #
b110100 *
1%
#156000
0%
#156500
b110101 *
b1 +
b0xxxxxx -
b10011100 #
1%
#157000
0%
#157500
b10011101 #
b110110 *
1%
#158000
0%
#158500
b110111 *
b10011110 #
1%
#159000
0%
#159500
b10011111 #
b111000 *
1%
#160000
0%
#160500
b111001 *
b10100000 #
1%
#161000
0%
#161500
b10100001 #
b111010 *
1%
#162000
0%
#162500
b111011 *
b10100010 #
1%
#163000
0%
#163500
b10100011 #
b111100 *
1%
#164000
0%
#164500
b111101 *
b10100100 #
1%
#165000
0%
#165500
b10100101 #
b111110 *
1%
#166000
0%
#166500
b111111 *
b10100110 #
1%
#167000
0%
#167500
b10100111 #
b1000000 *
1%
#168000
0%
#168500
b1000001 *
b10101000 #
1%
#169000
0%
#169500
b10101001 #
b1000010 *
1%
#170000
0%
#170500
b1000011 *
b10101010 #
1%
#171000
0%
#171500
b10101011 #
b1000100 *
1%
#172000
0%
#172500
b1000101 *
b10101100 #
1%
#173000
0%
#173500
b10101101 #
b1000110 *
1%
#174000
0%
#174500
b1000111 *
b10101110 #
1%
#175000
0%
#175500
b10101111 #
b1001000 *
1%
#176000
0%
#176500
b1001001 *
b10110000 #
1%
#177000
0%
#177500
b10110001 #
b1001010 *
1%
#178000
0%
#178500
b1001011 *
b10110010 #
1%
#179000
0%
#179500
b10110011 #
b1001100 *
1%
#180000
0%
#180500
b1001101 *
b10110100 #
1%
#181000
0%
#181500
b10110101 #
b1001110 *
1%
#182000
0%
#182500
b1001111 *
b10110110 #
1%
#183000
0%
#183500
b10110111 #
b1010000 *
1%
#184000
0%
#184500
b1010001 *
b10111000 #
1%
#185000
0%
#185500
b10111001 #
b1010010 *
1%
#186000
0%
#186500
b1010011 *
b10111010 #
1%
#187000
0%
#187500
b10111011 #
b1010100 *
1%
#188000
0%
#188500
b1010101 *
b10111100 #
1%
#189000
0%
#189500
b10111101 #
b1010110 *
1%
#190000
0%
#190500
b1010111 *
b10111110 #
1%
#191000
0%
#191500
b10111111 #
b1011000 *
1%
#192000
0%
#192500
b1011001 *
b11000000 #
1%
#193000
0%
#193500
b11000001 #
b1011010 *
1%
#194000
0%
#194500
b1011011 *
b11000010 #
1%
#195000
0%
#195500
b11000011 #
b1011100 *
1%
#196000
0%
#196500
b1011101 *
b11000100 #
1%
#197000
0%
#197500
b11000101 #
b1011110 *
1%
#198000
0%
#198500
b1011111 *
b11000110 #
1%
#199000
0%
#199500
b11000111 #
b1100000 *
1%
#200000
0%
#200500
b1100001 *
b11001000 #
1%
#201000
0%
#201500
b11001001 #
b1100010 *
1%
#202000
0%
#202500
b1100011 *
b11001010 #
1%
#203000
0%
#203500
b11001011 #
b1100100 *
1%
#204000
0%
#204500
b1100101 *
b11001100 #
1%
#205000
0%
#205500
b11001101 #
b1100110 *
1%
#206000
0%
#206500
b1100111 *
b11001110 #
1%
#207000
0%
#207500
b11001111 #
b1101000 *
1%
#208000
0%
#208500
b1 *
b11010000 #
1%
#209000
0%
b1 3
#209500
b11010001 #
b10 *
1%
#210000
0%
#210500
b11 *
b11010010 #
1%
#211000
0%
#211500
b11010011 #
b100 *
1%
#212000
0%
#212500
b101 *
b11010100 #
1%
#213000
0%
#213500
b11010101 #
b110 *
1%
#214000
0%
#214500
b111 *
b11010110 #
1%
#215000
0%
#215500
b11010111 #
b1000 *
1%
#216000
0%
#216500
b1001 *
b11011000 #
1%
#217000
0%
#217500
b11011001 #
b1010 *
1%
#218000
0%
#218500
b1011 *
b11011010 #
1%
#219000
0%
#219500
b11011011 #
b1100 *
1%
#220000
0%
#220500
b1101 *
b11011100 #
1%
#221000
0%
#221500
b11011101 #
b1110 *
1%
#222000
0%
#222500
b1111 *
b11011110 #
1%
#223000
0%
#223500
b11011111 #
b10000 *
1%
#224000
0%
#224500
b10001 *
b11100000 #
1%
#225000
0%
#225500
b11100001 #
b10010 *
1%
#226000
0%
#226500
b10011 *
b11100010 #
1%
#227000
0%
#227500
b11100011 #
b10100 *
1%
#228000
0%
#228500
b10101 *
b11100100 #
1%
#229000
0%
#229500
b11100101 #
b10110 *
1%
#230000
0%
#230500
b10111 *
b11100110 #
1%
#231000
0%
#231500
b11100111 #
b11000 *
1%
#232000
0%
#232500
b11001 *
b11101000 #
1%
#233000
0%
#233500
b11101001 #
b11010 *
1%
#234000
0%
#234500
b11011 *
b11101010 #
1%
#235000
0%
#235500
b11101011 #
b11100 *
1%
#236000
0%
#236500
b11101 *
b11101100 #
1%
#237000
0%
#237500
b11101101 #
b11110 *
1%
#238000
0%
#238500
b11111 *
b11101110 #
1%
#239000
0%
#239500
b11101111 #
b100000 *
1%
#240000
0%
#240500
b100001 *
b11110000 #
1%
#241000
0%
#241500
b11110001 #
b100010 *
1%
#242000
0%
#242500
b100011 *
b11110010 #
1%
#243000
0%
#243500
b11110011 #
b100100 *
1%
#244000
0%
#244500
b100101 *
b11110100 #
1%
#245000
0%
#245500
b11110101 #
b100110 *
1%
#246000
0%
#246500
b100111 *
b11110110 #
1%
#247000
0%
#247500
b11110111 #
b101000 *
1%
#248000
0%
#248500
b101001 *
b11111000 #
1%
#249000
0%
#249500
b11111001 #
b101010 *
1%
#250000
0%
#250500
b101011 *
b11111010 #
1%
#251000
0%
#251500
b11111011 #
b101100 *
1%
#252000
0%
#252500
b101101 *
b11111100 #
1%
#253000
0%
#253500
b11111101 #
b101110 *
1%
#254000
0%
#254500
b101111 *
b11111110 #
1%
#255000
0%
#255500
b11111111 #
b110000 *
1%
#256000
0%
#256500
b110001 *
b0 #
1%
#257000
0%
#257500
b1 #
b110010 *
1%
#258000
0%
#258500
b110011 *
b10 #
1%
#259000
0%
#259500
b11 #
b110100 *
1%
#260000
0%
#260500
b110101 *
b10 +
b0xxxxx -
b100 #
1%
#261000
0%
#261500
b101 #
b110110 *
1%
#262000
0%
#262500
b110111 *
b110 #
1%
#263000
0%
#263500
b111 #
b111000 *
1%
#264000
0%
#264500
b111001 *
b1000 #
1%
#265000
0%
#265500
b1001 #
b111010 *
1%
#266000
0%
#266500
b111011 *
b1010 #
1%
#267000
0%
#267500
b1011 #
b111100 *
1%
#268000
0%
#268500
b111101 *
b1100 #
1%
#269000
0%
#269500
b1101 #
b111110 *
1%
#270000
0%
#270500
b111111 *
b1110 #
1%
#271000
0%
#271500
b1111 #
b1000000 *
1%
#272000
0%
#272500
b1000001 *
b10000 #
1%
#273000
0%
#273500
b10001 #
b1000010 *
1%
#274000
0%
#274500
b1000011 *
b10010 #
1%
#275000
0%
#275500
b10011 #
b1000100 *
1%
#276000
0%
#276500
b1000101 *
b10100 #
1%
#277000
0%
#277500
b10101 #
b1000110 *
1%
#278000
0%
#278500
b1000111 *
b10110 #
1%
#279000
0%
#279500
b10111 #
b1001000 *
1%
#280000
0%
#280500
b1001001 *
b11000 #
1%
#281000
0%
#281500
b11001 #
b1001010 *
1%
#282000
0%
#282500
b1001011 *
b11010 #
1%
#283000
0%
#283500
b11011 #
b1001100 *
1%
#284000
0%
#284500
b1001101 *
b11100 #
1%
#285000
0%
#285500
b11101 #
b1001110 *
1%
#286000
0%
#286500
b1001111 *
b11110 #
1%
#287000
0%
#287500
b11111 #
b1010000 *
1%
#288000
0%
#288500
b1010001 *
b100000 #
1%
#289000
0%
#289500
b100001 #
b1010010 *
1%
#290000
0%
#290500
b1010011 *
b100010 #
1%
#291000
0%
#291500
b100011 #
b1010100 *
1%
#292000
0%
#292500
b1010101 *
b100100 #
1%
#293000
0%
#293500
b100101 #
b1010110 *
1%
#294000
0%
#294500
b1010111 *
b100110 #
1%
#295000
0%
#295500
b100111 #
b1011000 *
1%
#296000
0%
#296500
b1011001 *
b101000 #
1%
#297000
0%
#297500
b101001 #
b1011010 *
1%
#298000
0%
#298500
b1011011 *
b101010 #
1%
#299000
0%
#299500
b101011 #
b1011100 *
1%
#300000
0%
#300500
b1011101 *
b101100 #
1%
#301000
0%
#301500
b101101 #
b1011110 *
1%
#302000
0%
#302500
b1011111 *
b101110 #
1%
#303000
0%
#303500
b101111 #
b1100000 *
1%
#304000
0%
#304500
b1100001 *
b110000 #
1%
#305000
0%
#305500
b110001 #
b1100010 *
1%
#306000
0%
#306500
b1100011 *
b110010 #
1%
#307000
0%
#307500
b110011 #
b1100100 *
1%
#308000
0%
#308500
b1100101 *
b110100 #
1%
#309000
0%
#309500
b110101 #
b1100110 *
1%
#310000
0%
#310500
b1100111 *
b110110 #
1%
#311000
0%
#311500
b110111 #
b1101000 *
1%
#312000
0%
#312500
b1 *
b111000 #
1%
#313000
0%
b10 3
#313500
b111001 #
b10 *
1%
#314000
0%
#314500
b11 *
b111010 #
1%
#315000
0%
#315500
b111011 #
b100 *
1%
#316000
0%
#316500
b101 *
b111100 #
1%
#317000
0%
#317500
b111101 #
b110 *
1%
#318000
0%
#318500
b111 *
b111110 #
1%
#319000
0%
#319500
b111111 #
b1000 *
1%
#320000
0%
#320500
b1001 *
b1000000 #
1%
#321000
0%
#321500
b1000001 #
b1010 *
1%
#322000
0%
#322500
b1011 *
b1000010 #
1%
#323000
0%
#323500
b1000011 #
b1100 *
1%
#324000
0%
#324500
b1101 *
b1000100 #
1%
#325000
0%
#325500
b1000101 #
b1110 *
1%
#326000
0%
#326500
b1111 *
b1000110 #
1%
#327000
0%
#327500
b1000111 #
b10000 *
1%
#328000
0%
#328500
b10001 *
b1001000 #
1%
#329000
0%
#329500
b1001001 #
b10010 *
1%
#330000
0%
#330500
b10011 *
b1001010 #
1%
#331000
0%
#331500
b1001011 #
b10100 *
1%
#332000
0%
#332500
b10101 *
b1001100 #
1%
#333000
0%
#333500
b1001101 #
b10110 *
1%
#334000
0%
#334500
b10111 *
b1001110 #
1%
#335000
0%
#335500
b1001111 #
b11000 *
1%
#336000
0%
#336500
b11001 *
b1010000 #
1%
#337000
0%
#337500
b1010001 #
b11010 *
1%
#338000
0%
#338500
b11011 *
b1010010 #
1%
#339000
0%
#339500
b1010011 #
b11100 *
1%
#340000
0%
#340500
b11101 *
b1010100 #
1%
#341000
0%
#341500
b1010101 #
b11110 *
1%
#342000
0%
#342500
b11111 *
b1010110 #
1%
#343000
0%
#343500
b1010111 #
b100000 *
1%
#344000
0%
#344500
b100001 *
b1011000 #
1%
#345000
0%
#345500
b1011001 #
b100010 *
1%
#346000
0%
#346500
b100011 *
b1011010 #
1%
#347000
0%
#347500
b1011011 #
b100100 *
1%
#348000
0%
#348500
b100101 *
b1011100 #
1%
#349000
0%
#349500
b1011101 #
b100110 *
1%
#350000
0%
#350500
b100111 *
b1011110 #
1%
#351000
0%
#351500
b1011111 #
b101000 *
1%
#352000
0%
#352500
b101001 *
b1100000 #
1%
#353000
0%
#353500
b1100001 #
b101010 *
1%
#354000
0%
#354500
b101011 *
b1100010 #
1%
#355000
0%
#355500
b1100011 #
b101100 *
1%
#356000
0%
#356500
b101101 *
b1100100 #
1%
#357000
0%
#357500
b1100101 #
b101110 *
1%
#358000
0%
#358500
b101111 *
b1100110 #
1%
#359000
0%
#359500
b1100111 #
b110000 *
1%
#360000
0%
#360500
b110001 *
b1101000 #
1%
#361000
0%
#361500
b1101001 #
b110010 *
1%
#362000
0%
#362500
b110011 *
b1101010 #
1%
#363000
0%
#363500
b1101011 #
b110100 *
1%
#364000
0%
#364500
b110101 *
b11 +
b0xxxx -
b1101100 #
1%
#365000
0%
#365500
b1101101 #
b110110 *
1%
#366000
0%
#366500
b110111 *
b1101110 #
1%
#367000
0%
#367500
b1101111 #
b111000 *
1%
#368000
0%
#368500
b111001 *
b1110000 #
1%
#369000
0%
#369500
b1110001 #
b111010 *
1%
#370000
0%
#370500
b111011 *
b1110010 #
1%
#371000
0%
#371500
b1110011 #
b111100 *
1%
#372000
0%
#372500
b111101 *
b1110100 #
1%
#373000
0%
#373500
b1110101 #
b111110 *
1%
#374000
0%
#374500
b111111 *
b1110110 #
1%
#375000
0%
#375500
b1110111 #
b1000000 *
1%
#376000
0%
#376500
b1000001 *
b1111000 #
1%
#377000
0%
#377500
b1111001 #
b1000010 *
1%
#378000
0%
#378500
b1000011 *
b1111010 #
1%
#379000
0%
#379500
b1111011 #
b1000100 *
1%
#380000
0%
#380500
b1000101 *
b1111100 #
1%
#381000
0%
#381500
b1111101 #
b1000110 *
1%
#382000
0%
#382500
b1000111 *
b1111110 #
1%
#383000
0%
#383500
b1111111 #
b1001000 *
1%
#384000
0%
#384500
b1001001 *
b10000000 #
1%
#385000
0%
#385500
b10000001 #
b1001010 *
1%
#386000
0%
#386500
b1001011 *
b10000010 #
1%
#387000
0%
#387500
b10000011 #
b1001100 *
1%
#388000
0%
#388500
b1001101 *
b10000100 #
1%
#389000
0%
#389500
b10000101 #
b1001110 *
1%
#390000
0%
#390500
b1001111 *
b10000110 #
1%
#391000
0%
#391500
b10000111 #
b1010000 *
1%
#392000
0%
#392500
b1010001 *
b10001000 #
1%
#393000
0%
#393500
b10001001 #
b1010010 *
1%
#394000
0%
#394500
b1010011 *
b10001010 #
1%
#395000
0%
#395500
b10001011 #
b1010100 *
1%
#396000
0%
#396500
b1010101 *
b10001100 #
1%
#397000
0%
#397500
b10001101 #
b1010110 *
1%
#398000
0%
#398500
b1010111 *
b10001110 #
1%
#399000
0%
#399500
b10001111 #
b1011000 *
1%
#400000
0%
#400500
b1011001 *
b10010000 #
1%
#401000
0%
#401500
b10010001 #
b1011010 *
1%
#402000
0%
#402500
b1011011 *
b10010010 #
1%
#403000
0%
#403500
b10010011 #
b1011100 *
1%
#404000
0%
#404500
b1011101 *
b10010100 #
1%
#405000
0%
#405500
b10010101 #
b1011110 *
1%
#406000
0%
#406500
b1011111 *
b10010110 #
1%
#407000
0%
#407500
b10010111 #
b1100000 *
1%
#408000
0%
#408500
b1100001 *
b10011000 #
1%
#409000
0%
#409500
b10011001 #
b1100010 *
1%
#410000
0%
#410500
b1100011 *
b10011010 #
1%
#411000
0%
#411500
b10011011 #
b1100100 *
1%
#412000
0%
#412500
b1100101 *
b10011100 #
1%
#413000
0%
#413500
b10011101 #
b1100110 *
1%
#414000
0%
#414500
b1100111 *
b10011110 #
1%
#415000
0%
#415500
b10011111 #
b1101000 *
1%
#416000
0%
#416500
b1 *
b10100000 #
1%
#417000
0%
b11 3
#417500
b10100001 #
b10 *
1%
#418000
0%
#418500
b11 *
b10100010 #
1%
#419000
0%
#419500
b10100011 #
b100 *
1%
#420000
0%
#420500
b101 *
b10100100 #
1%
#421000
0%
#421500
b10100101 #
b110 *
1%
#422000
0%
#422500
b111 *
b10100110 #
1%
#423000
0%
#423500
b10100111 #
b1000 *
1%
#424000
0%
#424500
b1001 *
b10101000 #
1%
#425000
0%
#425500
b10101001 #
b1010 *
1%
#426000
0%
#426500
b1011 *
b10101010 #
1%
#427000
0%
#427500
b10101011 #
b1100 *
1%
#428000
0%
#428500
b1101 *
b10101100 #
1%
#429000
0%
#429500
b10101101 #
b1110 *
1%
#430000
0%
#430500
b1111 *
b10101110 #
1%
#431000
0%
